{    
    "Canada":"Canada",
    "USA":"United_States",
    "Austria":"Austria",
    "Belgium":"Belgium",
    "Denmark":"Denmark",
    "France":"France",
    "Netherlands":"Netherlands",
    "Italy":"Italy",
    "Norway":"Norway",
    "Spain":"Spain",
    "Sweden":"Sweden",
    "Switzerland":"Switzerland",
    "UK":"United_Kingdom",
    "Germany":"Germany",
    "Russia":"Russia",
    "Ukraine":"Ukraine",
    "Czech Republic":"Czech_Republic",
    "Poland":"Poland",
    "South Africa":"South_Africa",
    "Saudi Arabia":"Saudi_Arabia",
    "UAE":"United_Arab_Emirates",
    "Isreal":"Isreal",
    "Kuwait":"Kuwait",
    "Oman":"Oman",
    "China":"China",
    "Japan":"Japan",
    "Malaysia":"Malaysia",
    "Philippines":"Philippines",
    "Indonesia":"Indonesia",
    "Singapore":"Singapore",
    "Thailand":"Thailand",
    "South Korea":"South_Korea",
    "India":"India",
    "Maldives":"Maldives",
    "Pakistan":"Pakistan",
    "Bangladesh":"Bangladesh",
    "Australia":"Australia",
    "New Zealand":"New_Zealand"
}